ccai/__init__.py
ccai/client.py
examples/__init__.py
examples/cancel_sm_if_didnt_get_in_entry/__init__.py
examples/cancel_sm_if_didnt_get_in_entry/create_smart_order.py
examples/get_balances/__init__.py
examples/get_balances/get_balances.py
examples/many_targets/__init__.py
examples/many_targets/create_smart_order.py
examples/simple_smart_order/__init__.py
examples/simple_smart_order/create_smart_order.py
examples/trailing_entry_many_targets/__init__.py
examples/trailing_entry_many_targets/create_smart_order.py
examples/trailing_entry_trailing_exit/__init__.py
examples/trailing_entry_trailing_exit/create_smart_order.py
tests/__init__.py
ccai_client-0.0.5.dist-info/LICENSE
ccai_client-0.0.5.dist-info/METADATA
ccai_client-0.0.5.dist-info/WHEEL
ccai_client-0.0.5.dist-info/top_level.txt
ccai_client-0.0.5.dist-info/RECORD
