Metadata-Version: 2.1
Name: ccai-client
Version: 0.0.5
Summary: Cryptocurrencies.AI client library for trading
Home-page: https://github.com/Cryptocurrencies-AI/python-client-lib
Author: Cryptocurrencies.AI
Author-email: support@cryptocurrencies.ai
License: UNKNOWN
Platform: UNKNOWN
Classifier: Programming Language :: Python :: 3
Classifier: License :: OSI Approved :: GNU General Public License v3 or later (GPLv3+)
Classifier: Operating System :: OS Independent
Requires-Python: >=3.6
